dataPreprocessing/__init__.py
dataPreprocessing/categorical_encoder.py
dataPreprocessing/data_type_converter.py
dataPreprocessing/datetime_handler.py
dataPreprocessing/missing_value_handler.py
dataPreprocessing/outlier_handler.py
dataPreprocessing/test.py
dataPreprocessing/text_cleaner.py
src_omer_emir-0.3.dist-info/METADATA
src_omer_emir-0.3.dist-info/WHEEL
src_omer_emir-0.3.dist-info/top_level.txt
src_omer_emir-0.3.dist-info/RECORD
